README.md
setup.py
mageia/__init__.py
mageia/common.py
mageia/connection.py
mageia/db.py
mageia/loadbalance.py
mageia/proxy.py
mageia.egg-info/PKG-INFO
mageia.egg-info/SOURCES.txt
mageia.egg-info/dependency_links.txt
mageia.egg-info/not-zip-safe
mageia.egg-info/requires.txt
mageia.egg-info/top_level.txt