Metadata-Version: 2.1
Name: mageia
Version: 0.2.1
Summary: Simple DataBase tools for MySQL . Read Write Splitting Load Balance .
Home-page: https://github.com/stefanlei
Author: stefanlei
Author-email: stefanlei@qq.com
License: Apache
Platform: UNKNOWN
Classifier: Programming Language :: Python
Classifier: Operating System :: Microsoft :: Windows
Classifier: Operating System :: Unix
Classifier: Programming Language :: Python :: 2.7
Classifier: Programming Language :: Python :: 3.4
Classifier: Programming Language :: Python :: 3.5
Classifier: Programming Language :: Python :: 3.6
Classifier: Programming Language :: Python :: 3.7
Classifier: Programming Language :: Python :: 3.8
